sfdb/__init__.py
sfdb/sfdb.py
sfdb-0.1.0.dist-info/METADATA
sfdb-0.1.0.dist-info/WHEEL
sfdb-0.1.0.dist-info/RECORD
