Metadata-Version: 2.1
Name: sfdb
Version: 0.1.0
Summary: A single file implementation of key-value database for Python 3
Author: MohmadHabib
Author-email: mohmad.habib@gmail.com
Requires-Python: >=3.12,<4.0
Classifier: Programming Language :: Python :: 3
Classifier: Programming Language :: Python :: 3.12
Classifier: Programming Language :: Python :: 3.13
